MANIFEST.in
README.md
setup.cfg
setup.py
avrotool/__init__.py
avrotool/avrotool.py
avrotool.egg-info/PKG-INFO
avrotool.egg-info/SOURCES.txt
avrotool.egg-info/dependency_links.txt
avrotool.egg-info/entry_points.txt
avrotool.egg-info/requires.txt
avrotool.egg-info/top_level.txt