Metadata-Version: 1.1
Name: avrotool
Version: 0.0.2
Summary: Commandline Avro Toolbelt
Home-page: https://github.com/simonski/avrotool
Author: Simon Gauld
Author-email: simonski@github.com
License: MIT
Keywords: avro setuptools development
Platform: UNKNOWN
Classifier: Development Status :: 3 - Alpha
Classifier: Intended Audience :: Developers
Classifier: Topic :: Software Development :: Build Tools
Classifier: License :: OSI Approved :: MIT License
Classifier: Programming Language :: Python :: 2
Classifier: Programming Language :: Python :: 2.7
Classifier: Programming Language :: Python :: 3
Classifier: Programming Language :: Python :: 3.3
Classifier: Programming Language :: Python :: 3.4
Classifier: Programming Language :: Python :: 3.5
